configuration/__init__.py
configuration/configuration.py
connectors/__init__.py
connectors/aoai.py
connectors/blob.py
connectors/cosmosdb.py
connectors/doc_intelligence.py
connectors/fabric.py
connectors/keyvault.py
connectors/sqldbs.py
connectors/types.py
inputs/__init__.py
inputs/search_input.py
models/__init__.py
models/citation.py
models/types.py
prompts/__init__.py
resources/__init__.py
sse/__init__.py
sse/sse_server_transport.py
tools/__init__.py
tools/aisearch.py
tools/azureblob.py
tools/azuresql.py
tools/base_plugin.py
tools/bing.py
tools/code_interpreter_aca.py
tools/code_interpreter_ai_project.py
tools/cosmos.py
tools/databricks.py
tools/document_intelligence.py
tools/excel.py
tools/fabric.py
tools/lights_plugin.py
tools/mcp_server.py
tools/nl2sql.py
tools/restapi.py
tools/sharepoint.py
tools/wikipedia.py
gpt_rag_mcp-0.0.1.dist-info/LICENSE
gpt_rag_mcp-0.0.1.dist-info/METADATA
gpt_rag_mcp-0.0.1.dist-info/WHEEL
gpt_rag_mcp-0.0.1.dist-info/top_level.txt
gpt_rag_mcp-0.0.1.dist-info/RECORD
