Metadata-Version: 2.1
Name: gpt-rag-mcp
Version: 0.0.1
Summary: GPT RAG MCP (Model Context Protocol) library
Author: Microsoft Corporation
Author-email: v-cgivens@microsoft.com
Classifier: Programming Language :: Python :: 3
Classifier: License :: OSI Approved :: MIT License
Classifier: Operating System :: OS Independent
Requires-Python: >=3.9
License-File: LICENSE
